MANIFEST.in
README.rst
VERSION
setup.cfg
setup.py
npconf/__init__.py
npconf/main.py
npconf.egg-info/PKG-INFO
npconf.egg-info/SOURCES.txt
npconf.egg-info/dependency_links.txt
npconf.egg-info/top_level.txt
test/test_all.py