Metadata-Version: 1.1
Name: npconf
Version: 0.0.3
Summary: A flexible, intuitive native-python configuration system.
Home-page: https://github.com/stnbu/npconf
Author: Mike Burr
Author-email: mburr@unintuitive.org
License: MIT
Download-URL: https://github.com/stnbu/npconf/archive/master.zip
Keywords: configuration
Platform: UNKNOWN
Classifier: Development Status :: 4 - Beta
Classifier: Intended Audience :: Developers
Classifier: License :: OSI Approved :: MIT License
Classifier: Programming Language :: Python :: 2
Classifier: Topic :: Software Development
Classifier: Topic :: Utilities
Provides: npconf
